DeskripsiAngka/__init__.py
DeskripsiAngka/main.py
DeskripsiAngka/service/ganjigenap.py
DeskripsiAngka/service/prima.py
DeskripsiAngka-0.4.dist-info/METADATA
DeskripsiAngka-0.4.dist-info/WHEEL
DeskripsiAngka-0.4.dist-info/top_level.txt
DeskripsiAngka-0.4.dist-info/RECORD
