Metadata-Version: 2.1
Name: DeskripsiAngka
Version: 0.4
Summary: [ID] library untuk cek deskripsi dari suatu angka
Home-page: UNKNOWN
Author: UNKNOWN
Author-email: UNKNOWN
License: UNKNOWN
Platform: UNKNOWN
